{
  "generated_at": "2026-04-24T18:40:15.785563+00:00",
  "version": "1.0",
  "systems": [
    {
      "id": "cci",
      "name": "Crypto Cycle",
      "asset_class": "Crypto",
      "description": "Bitcoin & broader crypto cycle positioning",
      "icon": "₿",
      "color": "#f7931a",
      "dashboard_url": "https://jinhae8971.github.io/crypto-cycle-intelligence/",
      "axis": "x",
      "fetched_at": "2026-04-24T18:40:15.704197+00:00",
      "status": "ok",
      "score": 31.64,
      "subsystem_phase": "Accumulation",
      "phase": "Recovery",
      "phase_emoji": "🌱",
      "phase_color": "#3a8891",
      "dimensions": {
        "valuation": 26.68,
        "onchain": 20.97,
        "sentiment": 36.25,
        "derivatives": null,
        "macro": null,
        "technical": 49.53
      },
      "source_generated_at": "2026-04-24T13:14:11.148876+00:00",
      "stale_hours": 5.43
    },
    {
      "id": "asci",
      "name": "AI / Semiconductor",
      "asset_class": "Equities",
      "description": "AI infrastructure & semiconductor sector cycle",
      "icon": "🤖",
      "color": "#3b82f6",
      "dashboard_url": "https://jinhae8971.github.io/ai-semi-cycle-intelligence/",
      "axis": "y",
      "fetched_at": "2026-04-24T18:40:15.785474+00:00",
      "status": "ok",
      "score": 76.65,
      "subsystem_phase": "Late Bull",
      "phase": "Late Bull",
      "phase_emoji": "🔥",
      "phase_color": "#e76f51",
      "dimensions": {
        "valuation": 57.02,
        "earnings": 82.58,
        "capital": 73.57,
        "sentiment": 81.76,
        "macro": null,
        "technical": 99.45
      },
      "source_generated_at": "2026-04-24T18:04:52.993010+00:00",
      "stale_hours": 0.59
    }
  ],
  "insights": {
    "total_systems": 2,
    "active_systems": 2,
    "avg_score": 54.15,
    "spread": 45.01,
    "extreme_count": 0,
    "narratives": [
      {
        "type": "divergence",
        "title": "Major cross-asset divergence",
        "detail": "AI / Semiconductor (77, Late Bull) vs Crypto Cycle (32, Recovery) — spread 45"
      }
    ]
  }
}